[
  {
    "name": "GBA Emulator",
    "directory": "gba",
    "image": "icon.png",
    "recommended": "1"
  },
  {
    "name": "emulatorJS",
    "directory": "emulatorjs",
    "image": "logo.png"
  },
  {
    "name": "Pokemon | FireRed",
    "directory": "pokemon/firered",
    "image": ""
  },
  {
    "name": "Pokemon | LeafGreen",
    "directory": "pokemon/leafgreen",
    "image": ""
  },
  {
    "name": "Pokemon | Gold",
    "directory": "pokemon/gold",
    "image": ""
  },
  {
    "name": "Pokemon | Silver",
    "directory": "pokemon/silver",
    "image": ""
  },
  {
    "name": "Pokemon | Ruby",
    "directory": "pokemon/ruby",
    "image": ""
  },
  {
    "name": "Pokemon | Sapphire",
    "directory": "pokemon/sapphire",
    "image": ""
  },
    {
    "name": "Pokemon | Crystal",
    "directory": "pokemon/crystal",
    "image": ""
  },
  {
    "name": "Pokemon | Emerald",
    "directory": "pokemon/emerald",
    "image": ""
  },
  {
    "name": "Pokemon | Red",
    "directory": "pokemon/red",
    "image": ""
  },
    {
    "name": "Pokemon | Blue",
    "directory": "pokemon/blue",
    "image": ""
  },
    {
    "name": "Pokemon | Yellow",
    "directory": "pokemon/yellow",
    "image": ""
  }
]
